{
  "admin_positions": [
    {
      "group": "الإداريين",
      "rank": "اداري",
      "position": "مدير اداري"
    },
    {
      "group": "الإداريين",
      "rank": "اداري",
      "position": "مدير اداري"
    },
    {
      "group": "الإداريين",
      "rank": "اداري",
      "position": "مدير اداري"
    },
    {
      "group": "المهندسين",
      "rank": "مهندس مستشار",
      "position": "مدير صيانة"
    }
  ],
  "manager_positions": [
    {
      "group": "الإداريين",
      "rank": "اداري",
      "position": "أخصائي مراقبة موارد بشرية متقدم"
    },
    {
      "group": "الإداريين",
      "rank": "اداري",
      "position": "أخصائي مراقبة موارد بشرية ممارس أول"
    },
    {
      "group": "الإداريين",
      "rank": "اداري",
      "position": "أخصائي مراقبة موارد بشرية"
    },
    {
      "group": "الإداريين",
      "rank": "اداري",
      "position": "أخصائي مراقبة موارد بشرية ممارس"
    },
    {
      "group": "الإداريين",
      "rank": "اداري",
      "position": "مشرف امن وسلامه"
    },
    {
      "group": "الإداريين",
      "rank": "اداري",
      "position": "أخصائي مراقبة موارد بشرية ممارس"
    },
    {
      "group": "الإداريين",
      "rank": "اداري",
      "position": "مراقب امن وسلامة"
    },
    {
      "group": "الإداريين",
      "rank": "اداري",
      "position": "أخصائي مراقبة موارد بشرية مساعد"
    },
    {
      "group": "الإداريين",
      "rank": "اداري",
      "position": "مشرف مسكن ممارس ثالث"
    },
    {
      "group": "الإداريين",
      "rank": "اداري",
      "position": "مراقب امن وسلامة"
    },
    {
      "group": "الإداريين",
      "rank": "اداري",
      "position": "مراقب امن وسلامة"
    },
    {
      "group": "الإداريين",
      "rank": "اداري",
      "position": "مراقب امن وسلامة"
    },
    {
      "group": "الإداريين",
      "rank": "اداري",
      "position": "مراقب امن وسلامة"
    },
    {
      "group": "الإداريين",
      "rank": "اداري",
      "position": "مراقب مخزون مساعد"
    },
    {
      "group": "الإداريين",
      "rank": "اداري",
      "position": "مشرف مسكن ممارس ثالث"
    },
    {
      "group": "الإداريين",
      "rank": "اداري",
      "position": "أخصائي مراقبة موارد بشرية مساعد"
    },
    {
      "group": "الإداريين",
      "rank": "اداري",
      "position": "مراقب مخزون"
    },
    {
      "group": "الإداريين",
      "rank": "اداري",
      "position": "مراقب مخزون"
    },
    {
      "group": "الإداريين",
      "rank": "اداري",
      "position": "مراقب امن وسلامة"
    },
    {
      "group": "الإداريين",
      "rank": "اداري",
      "position": "مراقب امن وسلامة"
    },
    {
      "group": "الفنيين",
      "rank": "فني",
      "position": "فني مراقب وبائيات رجال"
    },
    {
      "group": "الفنيين",
      "rank": "فني",
      "position": "فني مراقب وبائيات رجال"
    }
  ],
  "specialist_positions": [
    {
      "group": "الأطباء",
      "rank": "طبيب نائب",
      "position": "طبيب نائب الباطنة العامة"
    },
    {
      "group": "الأطباء",
      "rank": "طبيب استشاري",
      "position": "طبيب استشاري الباطنة العامة"
    },
    {
      "group": "الأطباء",
      "rank": "طبيب استشاري",
      "position": "طبيب استشاري الجراحة العامة"
    },
    {
      "group": "الإداريين",
      "rank": "بند الأجور",
      "position": "عامل"
    },
    {
      "group": "الإداريين",
      "rank": "بند الأجور",
      "position": "عامل"
    },
    {
      "group": "الإداريين",
      "rank": "اداري",
      "position": "مساعد إداري ممارس أول"
    },
    {
      "group": "الإداريين",
      "rank": "اداري",
      "position": "مساعد إداري متقدم"
    },
    {
      "group": "الأطباء",
      "rank": "طبيب استشاري",
      "position": "طبيب استشاري طوارىء"
    },
    {
      "group": "الإداريين",
      "rank": "اداري",
      "position": "مساعد إداري متقدم"
    },
    {
      "group": "الأطباء",
      "rank": "طبيب استشاري",
      "position": "طبيب استشاري جراحة المسالك البولية"
    },
    {
      "group": "الإداريين",
      "rank": "اداري",
      "position": "مساعد إداري متقدم"
    },
    {
      "group": "الأطباء",
      "rank": "طبيب استشاري",
      "position": "طبيب استشاري الطب النفسي"
    },
    {
      "group": "الأطباء",
      "rank": "طبيب استشاري",
      "position": "طبيب استشاري الباطنة / قلب"
    },
    {
      "group": "الأطباء",
      "rank": "طبيب استشاري",
      "position": "طبيب استشاري الاسنان/علاج تحفظي واصلاح الاسنان"
    },
    {
      "group": "الأطباء",
      "rank": "طبيب استشاري",
      "position": "طبيب استشاري المختبرات / تشريح نسيجي"
    },
    {
      "group": "الأطباء",
      "rank": "طبيب استشاري",
      "position": "طبيب استشاري الاسنان/علاج تحفظي واصلاح الاسنان"
    },
    {
      "group": "الأطباء",
      "rank": "طبيب استشاري",
      "position": "طبيب استشاري الاسنان/علاج جذور الاسنان"
    },
    {
      "group": "الإداريين",
      "rank": "اداري",
      "position": "مساعد إداري ممارس أول"
    },
    {
      "group": "الأطباء",
      "rank": "طبيب استشاري",
      "position": "طبيب استشاري الباطنة / عناية مركزه"
    },
    {
      "group": "الأطباء",
      "rank": "طبيب نائب",
      "position": "طبيب نائب الجراحة العامة"
    },
    {
      "group": "الإداريين",
      "rank": "اداري",
      "position": "مساعد إداري ممارس أول"
    },
    {
      "group": "الأطباء",
      "rank": "طبيب استشاري",
      "position": "طبيب استشاري الباطنة/ امراض معديه"
    },
    {
      "group": "الإداريين",
      "rank": "اداري",
      "position": "مساعد إداري ممارس أول"
    },
    {
      "group": "الإداريين",
      "rank": "اداري",
      "position": "أخصائي علاقات عامة مساعد"
    },
    {
      "group": "الإداريين",
      "rank": "اداري",
      "position": "مساعد إداري ممارس أول"
    },
    {
      "group": "الأطباء",
      "rank": "طبيب استشاري",
      "position": "طبيب استشاري الاسنان / تقويم"
    },
    {
      "group": "الأطباء",
      "rank": "طبيب استشاري",
      "position": "طبيب استشاري الجراحة العامة"
    },
    {
      "group": "الأطباء",
      "rank": "طبيب استشاري",
      "position": "طبيب استشاري الاسنان / علاج وجراحة اللثة"
    },
    {
      "group": "الأطباء",
      "rank": "طبيب استشاري",
      "position": "طبيب استشاري الاسنان/علاج جذور الاسنان"
    },
    {
      "group": "الأطباء",
      "rank": "طبيب استشاري",
      "position": "طبيب استشاري طب وجراحة العظام"
    },
    {
      "group": "الأطباء",
      "rank": "طبيب نائب",
      "position": "طبيب نائب الجراحة العامة"
    },
    {
      "group": "الأطباء",
      "rank": "طبيب استشاري",
      "position": "طبيب استشاري المختبرات"
    },
    {
      "group": "الأطباء",
      "rank": "طبيب استشاري",
      "position": "طبيب استشاري المختبرات"
    },
    {
      "group": "الأطباء",
      "rank": "طبيب نائب",
      "position": "طبيب نائب الباطنة العامة"
    },
    {
      "group": "الأطباء",
      "rank": "طبيب استشاري",
      "position": "طبيب استشاري الباطنة / طب الاعصاب"
    },
    {
      "group": "الأطباء",
      "rank": "طبيب استشاري",
      "position": "طبيب استشاري الباطنة العامة"
    },
    {
      "group": "الأطباء",
      "rank": "طبيب استشاري",
      "position": "طبيب استشاري الباطنة العامة"
    },
    {
      "group": "الأطباء",
      "rank": "طبيب نائب",
      "position": "طبيب نائب الباطنة العامة"
    },
    {
      "group": "الأطباء",
      "rank": "طبيب استشاري",
      "position": "طبيب استشاري الباطنة العامة"
    },
    {
      "group": "الأطباء",
      "rank": "طبيب استشاري",
      "position": "طبيب استشاري الباطنة/ امراض معديه"
    },
    {
      "group": "الأطباء",
      "rank": "طبيب نائب",
      "position": "طبيب نائب الباطنة العامة"
    },
    {
      "group": "الأطباء",
      "rank": "طبيب استشاري",
      "position": "طبيب استشاري الباطنة / امراض الدم"
    },
    {
      "group": "الأطباء",
      "rank": "طبيب نائب",
      "position": "طبيب نائب الباطنة العامة"
    },
    {
      "group": "الأطباء",
      "rank": "طبيب نائب",
      "position": "طبيب نائب الباطنة العامة"
    },
    {
      "group": "الأطباء",
      "rank": "طبيب استشاري",
      "position": "طبيب استشاري الاسنان/ استعاضه سنيه"
    },
    {
      "group": "الأطباء",
      "rank": "طبيب نائب",
      "position": "طبيب نائب الباطنة العامة"
    },
    {
      "group": "الأطباء",
      "rank": "طبيب نائب",
      "position": "طبيب نائب الباطنة العامة"
    },
    {
      "group": "الأطباء",
      "rank": "طبيب استشاري",
      "position": "طبيب استشاري الجراحة العامة"
    },
    {
      "group": "الأطباء",
      "rank": "طبيب نائب",
      "position": "طبيب نائب الباطنة العامة"
    },
    {
      "group": "الأطباء",
      "rank": "طبيب استشاري",
      "position": "طبيب استشاري الاسنان/علاج تحفظي واصلاح الاسنان"
    }
  ],
  "commissioned_positions": [],
  "summary": {
    "total_employees": 1890,
    "admin_count": 4,
    "manager_count": 22,
    "specialist_count": 150,
    "commission_eligible": 0,
    "regular_staff": 1714
  }
}